matomo/__init__.py
matomo/django.py
matomo/request.py
matomo/tracker.py
matomo-1.0.0.dist-info/LICENSE
matomo-1.0.0.dist-info/METADATA
matomo-1.0.0.dist-info/WHEEL
matomo-1.0.0.dist-info/top_level.txt
matomo-1.0.0.dist-info/RECORD
